nonebot_plugin_general_whitelist-1.0.dist-info/METADATA
nonebot_plugin_general_whitelist-1.0.dist-info/WHEEL
nonebot_plugin_general_whitelist/__init__.py
nonebot_plugin_general_whitelist-1.0.dist-info/RECORD
